jafgen/__init__.py
jafgen/cli.py
jafgen/curves.py
jafgen/simulation.py
jafgen/customers/__init__.py
jafgen/customers/customers.py
jafgen/customers/order.py
jafgen/customers/order_item.py
jafgen/customers/tweet.py
jafgen/stores/__init__.py
jafgen/stores/inventory.py
jafgen/stores/item.py
jafgen/stores/market.py
jafgen/stores/stock.py
jafgen/stores/store.py
jafgen/stores/supply.py
jafgen-0.4.14.dist-info/LICENSE
jafgen-0.4.14.dist-info/METADATA
jafgen-0.4.14.dist-info/WHEEL
jafgen-0.4.14.dist-info/entry_points.txt
jafgen-0.4.14.dist-info/top_level.txt
jafgen-0.4.14.dist-info/RECORD
