Metadata-Version: 2.1
Name: jafgen
Version: 0.4.14
Summary: A synthetic data generator CLI for a fictional Jaffle Shop
Author-email: gwenwindflower <gwenwindflower@gmail.com>
License:                                  Apache License
License-File: LICENSE
Requires-Dist: numpy
Requires-Dist: Faker
Requires-Dist: typer
Provides-Extra: dev
Requires-Dist: ruff; extra == "dev"
Requires-Dist: pytest; extra == "dev"
